patchview/PatchView_pyinstaller.spec
patchview/PatchViewer.ico
patchview/__init__.py
patchview/__version__.py
patchview/enviroment-dev.yml
patchview/enviroment.yml
patchview/main.py
patchview/patchview.py
patchview/Data/JiangLab_protocols.yaml
patchview/Data/LICENSE.txt
patchview/Data/NDX_files
patchview/Data/Navigator.ui
patchview/Data/patchview.yaml
patchview/Data/icons/GP1.png
patchview/Data/icons/GP2.png
patchview/Data/icons/GPcorr.png
patchview/Data/icons/PatchViewer.ico
patchview/Data/icons/connection.png
patchview/Data/icons/connection2.png
patchview/Data/icons/navigation.png
patchview/Data/icons/neuron.png
patchview/Data/icons/rectangle.png
patchview/Data/icons/settings.png
patchview/Data/icons/spikes.png
patchview/Data/icons/tree.png
patchview/HekaIO/HEKA_Reader_MAIN.py
patchview/HekaIO/HekaHelpers.py
patchview/HekaIO/__init__.py
patchview/ephys/__init__.py
patchview/ephys/ephys_extractor.py
patchview/ephys/ephys_features.py
patchview/ephys/extraEhpys_PV.py
patchview/examples/load_spike_list.py
patchview/utilitis/AllMyParsHere.py
patchview/utilitis/AnalysisMethods.py
patchview/utilitis/PVdat2NWB.py
patchview/utilitis/__init__.py
patchview/utilitis/dandi2pvNWB.py
patchview/utilitis/debugHelpers.py
patchview/utilitis/emfDraw.py
patchview/utilitis/fitFuncs.py
patchview/utilitis/graphictools.py
patchview/utilitis/linecollection_update.py
patchview/utilitis/morphorFeatureExtrator.py
patchview/utilitis/patchviewObjects.py
patchview/utilitis/patchview_ndx.py
patchview/utilitis/pvEphy.py
patchview/utilitis/pvNDX_class.py
patchview/utilitis/pyqtgraph_helpers.py
patchview/utilitis/NDX_files/XiaolongJiangLab.extensions.yaml
patchview/utilitis/NDX_files/XiaolongJiangLab.namespace.yaml
patchview-0.3.7.dist-info/LICENSE
patchview-0.3.7.dist-info/METADATA
patchview-0.3.7.dist-info/WHEEL
patchview-0.3.7.dist-info/entry_points.txt
patchview-0.3.7.dist-info/top_level.txt
patchview-0.3.7.dist-info/RECORD
