Metadata-Version: 2.1
Name: patchview
Version: 0.3.7
Summary: Patchview perform data analysis and visualization on whole-cell recording data, including firing pattern analysis, event analysis, synatpic connection detection, morphorlocial analysis and more.
Home-page: https://github.com/zeitgeberH/patchview
Author: Ming Hu
Author-email: hi@gmail.com
License: BSD-3-Clause
Keywords: patchview
Classifier: Development Status :: 5 - Production/Stable
Classifier: Topic :: Scientific/Engineering :: Information Analysis
Classifier: Intended Audience :: End Users/Desktop
Classifier: License :: OSI Approved :: BSD License
Classifier: Development Status :: 5 - Production/Stable
Classifier: Topic :: Scientific/Engineering :: Information Analysis
Classifier: Intended Audience :: End Users/Desktop
Classifier: License :: OSI Approved :: BSD License
Classifier: Natural Language :: English
Classifier: Programming Language :: Python :: 3.10
Classifier: Operating System :: OS Independent
License-File: LICENSE
Requires-Dist: pyabf
Requires-Dist: furo
Requires-Dist: morphopy
Requires-Dist: colorcet
Requires-Dist: appdirs
Requires-Dist: Pillow
Requires-Dist: pynwb
Requires-Dist: tqdm
Requires-Dist: PySide2
Requires-Dist: pyqt5
Requires-Dist: pyqtwebengine
Requires-Dist: pyqt5-sip
Requires-Dist: pyqtgraph ==0.13.1
Requires-Dist: PyOpenGL
Requires-Dist: cython
Requires-Dist: neo
Requires-Dist: pylru ==1.2.1
Requires-Dist: h5py
Requires-Dist: joblib
Requires-Dist: future >=0.18.3
Requires-Dist: pyYAML
Requires-Dist: python-dateutil
Requires-Dist: seaborn
Requires-Dist: pytz
Requires-Dist: scipy <1.13
Requires-Dist: pandas
Requires-Dist: matplotlib
Requires-Dist: pycairo
Requires-Dist: scikit-image
Requires-Dist: morphio
Requires-Dist: scikit-learn
Requires-Dist: numpy <1.24,>=1.22
Requires-Dist: PyOpenGL-accelerate >=3.1.6 ; sys_platform == "win32"
Provides-Extra: dev
